DESCRIPTION.rst
LICENSE.md
MANIFEST.in
README.md
setup.py
bash/ec2tools-completion.bash
bash/iam_identities.py
bash/regions.list
bash/regions.py
bash/sizes.txt
ec2tools/__init__.py
ec2tools/_version.py
ec2tools/about.py
ec2tools/current_ami.py
ec2tools/environment.py
ec2tools/help_menu.py
ec2tools/launcher.py
ec2tools/logd.py
ec2tools/statics.py
ec2tools/text.py
ec2tools/user_selection.py
ec2tools/userdata.py
ec2tools/variables.py
ec2tools/__pycache__/__init__.cpython-38.pyc
ec2tools/__pycache__/_version.cpython-38.pyc
userdata/python2_generic.py
userdata/python3_generic.py
userdata/userdata.sh