Metadata-Version: 2.1
Name: ec2tools
Version: 0.6.25
Summary: Scripts & Tools for use with Amazon Web Services EC2 Service
Home-page: https://github.com/fstab50/ec2tools
Author: Blake Huber
Author-email: blakeca00@gmail.com
License: Apache
Keywords: aws amazon amazonlinux redhat centos ami tools
Platform: UNKNOWN
Classifier: Topic :: System :: Systems Administration
Classifier: Topic :: Utilities
Classifier: Development Status :: 4 - Beta
Classifier: Programming Language :: Python :: 3.6
Classifier: Programming Language :: Python :: 3.7
Classifier: Programming Language :: Python :: 3.8
Classifier: License :: OSI Approved :: GNU General Public License v3 (GPLv3)
Classifier: Operating System :: POSIX :: Linux
Classifier: Operating System :: Microsoft :: Windows
Requires-Python: >=3.6, <4
